ocr_data_toolkit/__init__.py
ocr_data_toolkit/odt.py
ocr_data_toolkit/common/__init__.py
ocr_data_toolkit/common/config.py
ocr_data_toolkit/data/__init__.py
ocr_data_toolkit/data/backgrounds/Screenshot 2023-12-15 143211.jpg
ocr_data_toolkit/data/backgrounds/Screenshot 2023-12-15 143220.jpg
ocr_data_toolkit/data/backgrounds/Screenshot 2023-12-15 143228.jpg
ocr_data_toolkit/data/backgrounds/Screenshot 2023-12-15 143240.jpg
ocr_data_toolkit/data/backgrounds/Screenshot 2023-12-15 143248.jpg
ocr_data_toolkit/data/backgrounds/Screenshot 2023-12-15 143306.jpg
ocr_data_toolkit/data/backgrounds/Screenshot 2023-12-15 143313.jpg
ocr_data_toolkit/data/backgrounds/Screenshot 2023-12-15 143322.jpg
ocr_data_toolkit/data/backgrounds/Screenshot 2023-12-15 143346.jpg
ocr_data_toolkit/data/backgrounds/Screenshot 2023-12-15 143353.jpg
ocr_data_toolkit/data/backgrounds/Screenshot 2023-12-15 143402.jpg
ocr_data_toolkit/data/backgrounds/Screenshot 2023-12-15 143409.jpg
ocr_data_toolkit/data/backgrounds/Screenshot 2023-12-15 143422.jpg
ocr_data_toolkit/data/backgrounds/Screenshot 2023-12-15 143429.jpg
ocr_data_toolkit/data/backgrounds/Screenshot 2023-12-15 143437.jpg
ocr_data_toolkit/data/backgrounds/Screenshot 2023-12-15 143453.jpg
ocr_data_toolkit/data/backgrounds/Screenshot 2023-12-15 143502.jpg
ocr_data_toolkit/data/backgrounds/Screenshot 2023-12-15 143530.jpg
ocr_data_toolkit/data/backgrounds/Screenshot 2023-12-15 143538.jpg
ocr_data_toolkit/data/backgrounds/Screenshot 2023-12-15 143545.jpg
ocr_data_toolkit/data/backgrounds/Screenshot 2023-12-15 143552.jpg
ocr_data_toolkit/data/backgrounds/Screenshot 2023-12-15 143601.jpg
ocr_data_toolkit/data/backgrounds/Screenshot 2023-12-15 143608.jpg
ocr_data_toolkit/data/backgrounds/Screenshot 2023-12-15 143614.jpg
ocr_data_toolkit/data/backgrounds/Screenshot 2023-12-15 143632.jpg
ocr_data_toolkit/data/backgrounds/Screenshot 2023-12-15 143638.jpg
ocr_data_toolkit/data/backgrounds/Screenshot 2023-12-15 143648.jpg
ocr_data_toolkit-0.1.2.dist-info/LICENSE
ocr_data_toolkit-0.1.2.dist-info/METADATA
ocr_data_toolkit-0.1.2.dist-info/WHEEL
ocr_data_toolkit-0.1.2.dist-info/top_level.txt
ocr_data_toolkit-0.1.2.dist-info/RECORD
