Metadata-Version: 2.1
Name: ocr-data-toolkit
Version: 0.1.2
Summary: A toolkit for generating synthetic data for OCR
Home-page: https://github.com/NaumanHSA/ocr-data-toolkit
Author: Muhammad Nouman Ahsan
Author-email: naumanhsa965@gmail.com
License: MIT
Classifier: Programming Language :: Python :: 3
Classifier: License :: OSI Approved :: MIT License
Classifier: Operating System :: OS Independent
Requires-Python: >=3.7
License-File: LICENSE
Requires-Dist: Pillow >=11.2.1
Requires-Dist: numpy >=1.24.1
Requires-Dist: opencv-python >=4.2.0
Requires-Dist: matplotlib >=3.5.1
Requires-Dist: atpbar >=2.0.3
